caryocar/__init__.py
caryocar/cleaning/__init__.py
caryocar/cleaning/misc.py
caryocar/cleaning/namesatomizer.py
caryocar/cleaning/namesmap.py
caryocar/cleaning/tests/__init__.py
caryocar/cleaning/tests/test_cleaning.py
caryocar/models/__init__.py
caryocar/models/cwn.py
caryocar/models/scn.py
caryocar/models/tests/__init__.py
caryocar/models/tests/test_cwn.py
caryocar-0.0.1.dist-info/METADATA
caryocar-0.0.1.dist-info/RECORD
caryocar-0.0.1.dist-info/WHEEL
caryocar-0.0.1.dist-info/top_level.txt
